Metadata-Version: 2.1
Name: cfgsaver
Version: 1.0.4
Summary: Module to save and fetch configuration data in a standard path and format.
Home-page: https://github.com/prahladyeri/cfgsaver
Author: Prahlad Yeri
Author-email: prahladyeri@yahoo.com
License: MIT
Platform: UNKNOWN
Classifier: Programming Language :: Python :: 3
Classifier: License :: OSI Approved :: MIT License
Classifier: Operating System :: OS Independent
Requires-Python: >= 3.4
